LICENSE.txt
MANIFEST.in
README.rst
oraide_voiceover.rst
places_to_change_version_numbers.txt
requirements.txt
setup.py
tox.ini
Oraide.egg-info/PKG-INFO
Oraide.egg-info/SOURCES.txt
Oraide.egg-info/dependency_links.txt
Oraide.egg-info/top_level.txt
docs/Makefile
docs/api.rst
docs/conf.py
docs/conf.pyc
docs/history.rst
docs/index.rst
docs/no-hands.gif
docs/priorart.rst
docs/refresh_chrome.sh
docs/requirements-spelling.txt
docs/requirements.txt
docs/spelling_wordlist.txt
docs/tutorial.rst
docs/watchdocs.py
docs/whentouse.rst
examples/session.py
examples/simple.py
oraide/__init__.py
oraide/keys.py
oraide/tests.py
oraide.egg-info/SOURCES.txt