Metadata-Version: 1.1
Name: oraide
Version: 0.4
Summary: A library to help presenters demonstrate terminal sessions hands-free.
Home-page: https://github.com/ddbeck/oraide
Author: Daniel D. Beck
Author-email: me@danieldbeck.com
License: BSD
Keywords: tmux,presentation,demonstration
Platform: UNKNOWN
Classifier: Development Status :: 4 - Beta
Classifier: Environment :: Console
Classifier: License :: OSI Approved :: BSD License
Classifier: Operating System :: POSIX
Classifier: Programming Language :: Python :: 2.7
Classifier: Programming Language :: Python :: 3.3
Classifier: Topic :: System :: Shells
Classifier: Topic :: Terminals
Classifier: Topic :: Utilities
